deepmcpagent/__init__.py
deepmcpagent/__main__.py
deepmcpagent/agent.py
deepmcpagent/cli.py
deepmcpagent/clients.py
deepmcpagent/config.py
deepmcpagent/cross_agent.py
deepmcpagent/prompt.py
deepmcpagent/py.typed
deepmcpagent/tools.py
deepmcpagent-0.5.0.dist-info/licenses/LICENSE
deepmcpagent-0.5.0.dist-info/METADATA
deepmcpagent-0.5.0.dist-info/WHEEL
deepmcpagent-0.5.0.dist-info/entry_points.txt
deepmcpagent-0.5.0.dist-info/top_level.txt
deepmcpagent-0.5.0.dist-info/RECORD
