Metadata-Version: 2.4
Name: deepmcpagent
Version: 0.5.0
Summary: DeepMCPAgent: LangChain/LangGraph agents powered by MCP tools over FastMCP.
Author: cryxnet
License: Apache-2.0
Project-URL: Homepage, https://github.com/cryxnet/deepmcpagent
Project-URL: Issues, https://github.com/cryxnet/deepmcpagent/issues
Keywords: mcp,fastmcp,langchain,langgraph,agents,tools
Classifier: Programming Language :: Python :: 3
Classifier: Programming Language :: Python :: 3 :: Only
Classifier: License :: OSI Approved :: Apache Software License
Classifier: Development Status :: 4 - Beta
Classifier: Typing :: Typed
Classifier: Topic :: Software Development :: Libraries
Requires-Python: >=3.10
License-File: LICENSE
Requires-Dist: fastmcp>=2.12.2
Requires-Dist: langchain>=0.3.27
Requires-Dist: pydantic>=2.8
Requires-Dist: typer>=0.15.2
Requires-Dist: rich>=14
Requires-Dist: anyio>=4.5
Requires-Dist: python-dotenv>=1.1
Requires-Dist: langgraph<0.7,>=0.6
Requires-Dist: langgraph-prebuilt<0.7,>=0.6
Provides-Extra: deep
Requires-Dist: deepagents<1.0,>=0.0.5; extra == "deep"
Provides-Extra: docs
Requires-Dist: mkdocs>=1.6; extra == "docs"
Requires-Dist: mkdocs-material>=9.5; extra == "docs"
Requires-Dist: mkdocstrings[python]>=0.29; extra == "docs"
Provides-Extra: examples
Requires-Dist: langchain-openai>=0.3.30; extra == "examples"
Provides-Extra: dev
Requires-Dist: pytest>=8.4; extra == "dev"
Requires-Dist: pytest-asyncio>=1.1; extra == "dev"
Requires-Dist: mypy>=1.17; extra == "dev"
Requires-Dist: ruff>=0.12; extra == "dev"
Dynamic: license-file
